{
	"animations": [
		{
			"offsets": [
				-5,
				0
			],
			"frameIndices": [],
			"prefix": "sonic Idle",
			"looped": false,
			"name": "idle",
			"interrupt": true,
			"flipX": false,
			"nextAnim": "idle",
			"flipY": false,
			"frameRate": 24
		},
		{
			"offsets": [
				-1,
				-4
			],
			"frameIndices": [],
			"prefix": "sonic Up",
			"looped": false,
			"name": "singUP",
			"interrupt": true,
			"flipX": false,
			"nextAnim": "idle",
			"flipY": false,
			"frameRate": 24
		},
		{
			"offsets": [
				9,
				-6
			],
			"frameIndices": [],
			"prefix": "sonic Left",
			"looped": false,
			"name": "singLEFT",
			"interrupt": true,
			"flipX": false,
			"nextAnim": "idle",
			"flipY": false,
			"frameRate": 24
		},
		{
			"offsets": [
				-8,
				7
			],
			"frameIndices": [],
			"prefix": "sonic Right",
			"looped": false,
			"name": "singRIGHT",
			"interrupt": true,
			"flipX": false,
			"nextAnim": "idle",
			"flipY": false,
			"frameRate": 24
		},
		{
			"offsets": [
				10,
				0
			],
			"frameIndices": [],
			"prefix": "sonic Down",
			"looped": false,
			"name": "singDOWN",
			"interrupt": true,
			"flipX": false,
			"nextAnim": "idle",
			"flipY": false,
			"frameRate": 24
		},
		{
			"offsets": [
				37,
				11
			],
			"frameIndices": [],
			"prefix": "sonic Sonic dies",
			"looped": false,
			"name": "firstDeath",
			"interrupt": false,
			"flipX": false,
			"nextAnim": "deathLoop",
			"flipY": false,
			"frameRate": 24
		},
		{
			"offsets": [
				37,
				15
			],
			"frameIndices": [],
			"prefix": "sonic Dead Loop",
			"looped": true,
			"name": "deathLoop",
			"interrupt": false,
			"flipX": false,
			"nextAnim": "deathLoop",
			"flipY": false,
			"frameRate": 24
		},
		{
			"offsets": [
				37,
				19
			],
			"frameIndices": [],
			"prefix": "sonic death Confirm",
			"looped": false,
			"name": "deathConfirm",
			"interrupt": false,
			"flipX": false,
			"nextAnim": "idle",
			"flipY": false,
			"frameRate": 24
		}
	],
	"hasTrail": false,
	"camPos": [
		250,
		-55
	],
	"holdLength": 4,
	"charPos": [
		10,
		160
	],
	"flipX": true,
	"asset": "characters/sonic",
	"startingAnim": "idle",
	"characterIcon": "icon-sonic",
	"antialiasing": true,
	"name": "characters/sonic",
	"barColorJson": [
		47,
		111,
		231
	],
	"replacesGF": false,
	"scale": 0
}